winbackup/__init__.py
winbackup/__main__.py
winbackup/configagent.py
winbackup/systemconfigsaver.py
winbackup/winbackup.py
winbackup/windowspaths.py
winbackup/zip7archiver.py
winbackup/bin/7z/7z.dll
winbackup/bin/7z/7z.exe
winbackup/scripts/CONTRIBUTING.md
winbackup/scripts/LICENSE
winbackup/scripts/README.md
winbackup/scripts/config.ps1
winbackup/scripts/hyperv_paths.ps1
winbackup/scripts/installed_programs.ps1
winbackup/scripts/winfetch.ps1
winbackup-0.2.0b0.dist-info/LICENSE
winbackup-0.2.0b0.dist-info/METADATA
winbackup-0.2.0b0.dist-info/WHEEL
winbackup-0.2.0b0.dist-info/entry_points.txt
winbackup-0.2.0b0.dist-info/top_level.txt
winbackup-0.2.0b0.dist-info/RECORD
