Metadata-Version: 2.1
Name: winbackup
Version: 0.2.0b0
Summary: Backup user files on windows to 7z archives
Home-page: https://github.com/needs-coffee/winbackup
Author: Joe Campbell
License: GPLv3
Project-URL: Bug Tracker, https://github.com/needs-coffee/winbackup/issues
Keywords: windows backup virtualbox plex backup-script hyper-v backup-tool 7zip
Classifier: Programming Language :: Python :: 3
Classifier: License :: OSI Approved :: GNU General Public License v3 (GPLv3)
Classifier: Development Status :: 4 - Beta
Classifier: Operating System :: Microsoft :: Windows
Classifier: Natural Language :: English
Classifier: Topic :: Utilities
Requires-Python: >=3.7
License-File: LICENSE
Requires-Dist: tqdm (>4)
Requires-Dist: colorama (>0.4)
Requires-Dist: Send2Trash (>1.5)
Requires-Dist: humanize (>4)
Requires-Dist: PyYAML (>5)
